{
  "defaultGroup": "USAGE",
  "showMeasuredInOverview": true,
  "supportedWidgets": [
    "MediumInformationWidgetView"
  ],
  "states": [
    {
      "key": "electricityPower",
      "showInOverview": true,
      "markers": [
        "WidgetMediumLine1"
      ]
    },
    {
      "key": "electricityConsumed",
      "showInOverview": true,
      "markers": [
        "WidgetMediumLine2"
      ]
    }
  ],
  "sanitise": {
    "electricityConsumed": {
      "append": "kWh",
      "extract": "int"
    },
    "electricityPower": {
      "append": "W",
      "extract": "int"
    }
  }
}